ctgforge/__init__.py
ctgforge/client/ctg_client.py
ctgforge/client/httpx_client.py
ctgforge/client/requests_client.py
ctgforge/ctg.py
ctgforge/export/__init__.py
ctgforge/export/dataframe.py
ctgforge/export/graph.py
ctgforge/flatten/__init__.py
ctgforge/flatten/core.py
ctgforge/models/core.py
ctgforge/query/compiler.py
ctgforge/query/expr.py
ctgforge/query/fields.py
ctgforge/query/specs.py
ctgforge-0.2.5.dist-info/WHEEL
ctgforge-0.2.5.dist-info/METADATA
ctgforge-0.2.5.dist-info/RECORD
