Metadata-Version: 2.3
Name: ctgforge
Version: 0.2.5
Summary: Turn ClinicalTrials.gov v2 studies into analytics-ready DataFrames and knowledge graphs.
Keywords: clinical trials,clinicaltrials.gov,biomedical data,healthcare data,bioinformatics,knowledge graph,dataframe,clinical research
Author: littledumb
Author-email: littledumb <jiamin@gmail.com>
Classifier: Development Status :: 3 - Alpha
Classifier: Intended Audience :: Science/Research
Classifier: Intended Audience :: Developers
Classifier: Intended Audience :: Healthcare Industry
Classifier: Topic :: Scientific/Engineering
Classifier: Topic :: Scientific/Engineering :: Bio-Informatics
Classifier: Topic :: Scientific/Engineering :: Medical Science Apps.
Classifier: Topic :: Database
Classifier: Topic :: Software Development :: Libraries :: Python Modules
Classifier: License :: OSI Approved :: MIT License
Classifier: Programming Language :: Python
Classifier: Programming Language :: Python :: 3
Classifier: Programming Language :: Python :: 3 :: Only
Classifier: Programming Language :: Python :: 3.9
Classifier: Programming Language :: Python :: 3.10
Classifier: Programming Language :: Python :: 3.11
Classifier: Programming Language :: Python :: 3.12
Classifier: Operating System :: OS Independent
Requires-Dist: httpx>=0.28.1
Requires-Dist: pandas>=2.3.3
Requires-Dist: pydantic>=2.12.5
Requires-Dist: requests>=2.32.5 ; extra == 'requests'
Requires-Python: >=3.9
Provides-Extra: requests
